setup.py
easysendemail/Email.py
easysendemail/__init__.py
easysendemail.egg-info/PKG-INFO
easysendemail.egg-info/SOURCES.txt
easysendemail.egg-info/dependency_links.txt
easysendemail.egg-info/top_level.txt
easysendemail.egg-info/zip-safe