Metadata-Version: 1.0
Name: easysendemail
Version: 1.0.2
Summary: A simple package to send email.
Home-page: UNKNOWN
Author: Klein
Author-email: juhongxiaoshou@163.com
License: UNKNOWN
Keywords: email
Platform: UNKNOWN
